internal_unit_testing.py
src/__init__.py
src/internal_unit_testing.py
cloud_composer_dag_test_utils-1.0.0.dist-info/METADATA
cloud_composer_dag_test_utils-1.0.0.dist-info/WHEEL
cloud_composer_dag_test_utils-1.0.0.dist-info/top_level.txt
cloud_composer_dag_test_utils-1.0.0.dist-info/RECORD
