Metadata-Version: 2.1
Name: cloud-composer-dag-test-utils
Version: 1.0.0
Summary: Utility used to unit test example Apache Airflow DAGs for Google Cloud Composer. This is not an officially supported Google product.
Home-page: https://github.com/GoogleCloudPlatform/python-docs-samples/tree/master/composer/dag_test_utils
Author: Google LLC
License: UNKNOWN
Platform: UNKNOWN
Requires-Dist: apache-airflow[google] (<3.0.0,>=2.0.0)
